{
  "asOf": "2026-05-12",
  "prices": {
    "DFAI": 41.44,
    "DFIV": 55.39,
    "DGS": 64.23,
    "VNQI": 47.34,
    "DFAR": 26.01,
    "VGLT": 54.38,
    "SCHG": 34.07,
    "TLT": 84.99,
    "DFSV": 36.93,
    "SCHX": 29.01,
    "VIOO": 125.52,
    "DFEV": 41.26,
    "VNQ": 96.69,
    "DFIS": 36.33,
    "SCHM": 34.51,
    "IMCV": 88.53,
    "DISV": 42.16,
    "DFUV": 52.59,
    "DFAU": 50.7,
    "DFAT": 66.22,
    "SHYM": 22.16,
    "DFAE": 39.01,
    "VSS": 160.42,
    "VTEB": 50.12,
    "PZA": 23.27,
    "IMCG": 89.96,
    "HYD": 51.01,
    "BNDX": 47.81,
    "IWC": 185.25,
    "EFG": 120.34,
    "DFIP": 42.165,
    "DFGX": 52.545,
    "IEMG": 80.46,
    "VONV": 102.77,
    "ISCG": 61.27,
    "DFAS": 76.85
  },
  "missing": []
}