{
  "asOf": "2026-03-23",
  "prices": {
    "TLT": 86.385,
    "SCHG": 29.71,
    "DFAU": 45.44,
    "DFUV": 48.285,
    "DGS": 60.35,
    "DFAI": 38.515,
    "DFAT": 61.6,
    "VNQI": 44.59,
    "SHYM": 22.105,
    "DISV": 38.53,
    "DFEV": 36.1,
    "DFIS": 33.17,
    "DFAE": 34.22,
    "VSS": 144.48,
    "IMCV": 83.68,
    "VIOO": 113.654,
    "SCHM": 30.96,
    "DFAR": 23.605,
    "VTEB": 49.93,
    "DFIV": 51.76,
    "PZA": 22.92,
    "IMCG": 79.59,
    "IWC": 160.33,
    "HYD": 50.35,
    "DFIP": 41.66,
    "DFGX": 52.3,
    "IEMG": 70.46,
    "BNDX": 48.005,
    "EFG": 111.39,
    "VGLT": 55.125
  },
  "missing": []
}