{
  "asOf": "2026-02-17",
  "prices": {
    "TLT": 89.87,
    "SCHG": 30.6302,
    "DFAU": 47.465,
    "DFUV": 50.24,
    "DGS": 63.685,
    "DFAI": 41.5734,
    "DFAT": 66.14,
    "VNQI": 50.525,
    "SHYM": 22.46,
    "DISV": 42.485,
    "DFEV": 37.81,
    "DFIS": 36.3201,
    "DFAE": 36.26,
    "VSS": 156.74,
    "IMCV": 88.7,
    "VIOO": 121.0403,
    "SCHM": 32.61,
    "DFAR": 25.21,
    "VTEB": 50.865,
    "DFIV": 55.18,
    "PZA": 23.465,
    "IMCG": 82.85,
    "IWC": 167.415,
    "HYD": 51.315,
    "DFIP": 42.075,
    "DFGX": 53.455,
    "IEMG": 74.91,
    "BNDX": 48.895,
    "EFG": 121.98,
    "VGLT": 57.285
  },
  "missing": []
}