{
  "asOf": "2026-04-22",
  "prices": {
    "DFAI": 40.83,
    "DFIV": 54.46,
    "DGS": 64.63,
    "VNQI": 47.22,
    "DFAR": 25.165,
    "VGLT": 55.45,
    "SCHG": 32.85,
    "TLT": 86.75,
    "DFSV": 37.17,
    "SCHX": 28.04,
    "VIOO": 125.36,
    "DFEV": 39.67,
    "VNQ": 94.52,
    "DFIS": 35.66,
    "SCHM": 33.77,
    "IMCV": 88.34,
    "DISV": 41.07,
    "DFUV": 51.04,
    "DFAU": 49.2,
    "DFAT": 66.37,
    "SHYM": 22.2098,
    "DFAE": 37.79,
    "VSS": 157.96,
    "VTEB": 50.43,
    "PZA": 23.29,
    "IMCG": 87.44,
    "HYD": 51.18,
    "BNDX": 48.17,
    "IWC": 181.06,
    "EFG": 119.47,
    "DFIP": 42.055,
    "DFGX": 52.865,
    "IEMG": 77.9,
    "VONV": 99.39,
    "ISCG": 60.69,
    "DFAS": 77.0
  },
  "missing": []
}