{
  "asOf": "2026-05-19",
  "prices": {
    "DFAI": 40.855,
    "DFIV": 55.03,
    "DGS": 62.92,
    "VNQI": 45.59,
    "DFAR": 25.735,
    "VGLT": 53.19,
    "SCHG": 33.89,
    "TLT": 83.015,
    "DFSV": 36.47,
    "SCHX": 28.83,
    "VIOO": 123.08,
    "DFEV": 40.22,
    "VNQ": 95.28,
    "DFIS": 35.68,
    "SCHM": 33.56,
    "IMCV": 87.95,
    "DISV": 41.57,
    "DFUV": 52.08,
    "DFAU": 50.3,
    "DFAT": 65.21,
    "SHYM": 22.06,
    "DFAE": 38.05,
    "VSS": 155.75,
    "VTEB": 49.68,
    "PZA": 22.85,
    "IMCG": 88.065,
    "HYD": 50.49,
    "BNDX": 47.585,
    "IWC": 176.56,
    "EFG": 118.04,
    "DFIP": 41.525,
    "DFGX": 52.27,
    "IEMG": 78.53,
    "VONV": 101.65,
    "ISCG": 59.35,
    "DFAS": 75.14
  },
  "missing": []
}